DeepBrainSeg/__init__.py
DeepBrainSeg/src/Tester.py
DeepBrainSeg/src/__init__.py
DeepBrainSeg/src/brats_tester.py
DeepBrainSeg/src/helper.py
DeepBrainSeg/src/helper_mask.py
DeepBrainSeg/src/npanalysis.py
DeepBrainSeg/src/models/__init__.py
DeepBrainSeg/src/models/layers2DABL.py
DeepBrainSeg/src/models/layersTir2D.py
DeepBrainSeg/src/models/layersTir3D.py
DeepBrainSeg/src/models/model3DBNET.py
DeepBrainSeg/src/models/modelABL.py
DeepBrainSeg/src/models/modelTir2D.py
DeepBrainSeg/src/models/modelTir3D.py
ui/DeepBrainSeg1.py
ui/DeepBrainSeg1_support.py
ui/DeepBrainSegUI.py
ui/DeepBrainSegUI_support.py
ui/__init__.py
ui/helpers.py
DeepBrainSeg-0.1.8.dist-info/METADATA
DeepBrainSeg-0.1.8.dist-info/WHEEL
DeepBrainSeg-0.1.8.dist-info/top_level.txt
DeepBrainSeg-0.1.8.dist-info/RECORD
