Metadata-Version: 2.1
Name: DeepBrainSeg
Version: 0.1.8
Summary: Deep Learning tool for brain tumor segmentation.
Home-page: https://github.com/koriavinash1/DeepBrainSeg
Author: Avinash Kori
Author-email: koriavinash1@gmail.com
License: UNKNOWN
Platform: UNKNOWN
Classifier: Programming Language :: Python :: 3.5
Classifier: License :: OSI Approved :: MIT License
Classifier: Operating System :: OS Independent
Requires-Dist: googledrivedownloader
Requires-Dist: torch
Requires-Dist: torchvision
Requires-Dist: nibabel
Requires-Dist: SimpleITK
Requires-Dist: tqdm
Requires-Dist: pandas
Requires-Dist: scipy
Requires-Dist: pydensecrf
Requires-Dist: scikit-image
